INSTALL.md
LICENSE
README.md
biggan/__init__.py
biggan/architecture/__init__.py
biggan/architecture/attention.py
biggan/architecture/conditional_batch_normalization.py
biggan/architecture/discriminator.py
biggan/architecture/generator.py
biggan/architecture/spectral_normalization.py
biggan/config/__init__.py
biggan/config/base.yaml
biggan/data.py
biggan/model.py
biggan/scripts/__init__.py
biggan/scripts/prepare.py
biggan/scripts/train.py
biggan-1.0.0a1.dist-info/entry_points.txt
biggan-1.0.0a1.dist-info/LICENSE
biggan-1.0.0a1.dist-info/WHEEL
biggan-1.0.0a1.dist-info/METADATA
biggan-1.0.0a1.dist-info/RECORD
